fix_plugin_slack/__init__.py
fix_plugin_slack/config.py
fix_plugin_slack/resources.py
fixinventory_plugin_slack-4.2.0.dist-info/METADATA
fixinventory_plugin_slack-4.2.0.dist-info/WHEEL
fixinventory_plugin_slack-4.2.0.dist-info/entry_points.txt
fixinventory_plugin_slack-4.2.0.dist-info/top_level.txt
fixinventory_plugin_slack-4.2.0.dist-info/RECORD
